rsmine/__init__.py
rsmine/coarsegrainer/__init__.py
rsmine/coarsegrainer/analysis_utils.py
rsmine/coarsegrainer/build_dataset.py
rsmine/coarsegrainer/cg_layers.py
rsmine/coarsegrainer/cg_optimisers.py
rsmine/coarsegrainer/cg_sequels.py
rsmine/coarsegrainer/cg_utils.py
rsmine/coarsegrainer/exec_coarsegrainer.py
rsmine/coarsegrainer/plotter.py
rsmine/mi_estimator/MI_estimators.py
rsmine/mi_estimator/VBMI_bounds.py
rsmine/mi_estimator/VBMI_estimators.py
rsmine/mi_estimator/__init__.py
rsmine/mi_estimator/critics.py
rsmine/mi_estimator/utils.py
rsmine-0.3.0a1.dist-info/LICENSE
rsmine-0.3.0a1.dist-info/METADATA
rsmine-0.3.0a1.dist-info/WHEEL
rsmine-0.3.0a1.dist-info/top_level.txt
rsmine-0.3.0a1.dist-info/RECORD
