Metadata-Version: 2.1
Name: rsmine
Version: 0.3.0a1
Summary: Optimal coarse graining transformations with RSMI neural estimation
Home-page: https://github.com/RSMI-NE/RSMI-NE
Author: Doruk Efe Gökmen, Maciej Koch-Janusz
Author-email: dgoekmen@ethz.ch
License: Apache License 2.0
Project-URL: Source, https://github.com/RSMI-NE/RSMI-NE
Project-URL: Bug Tracker, https://github.com/RSMI-NE/RSMI-NE/issues
Keywords: renormalization
Classifier: Development Status :: 3 - Alpha
Classifier: Intended Audience :: Science/Research
Classifier: Intended Audience :: Education
Classifier: Topic :: Scientific/Engineering :: Physics
Classifier: Topic :: Scientific/Engineering :: Artificial Intelligence
Classifier: Programming Language :: Python :: 3.6
Classifier: Programming Language :: Python :: 3.7
Classifier: Programming Language :: Python :: 3.8
Classifier: Programming Language :: Python :: 3.9
Requires-Python: >=3.6
License-File: LICENSE
Requires-Dist: requests
Requires-Dist: numpy
Requires-Dist: tensorflow-macos
Requires-Dist: tensorflow-probability
Requires-Dist: pandas
Requires-Dist: matplotlib
Requires-Dist: wandb
Requires-Dist: tqdm
Requires-Dist: networkx
Requires-Dist: scipy
Requires-Dist: seaborn
Requires-Dist: scikit-learn
